aycolor/__init__.py
aycolor/color.py
aycolor-0.0.1.dist-info/LICENSE
aycolor-0.0.1.dist-info/METADATA
aycolor-0.0.1.dist-info/WHEEL
aycolor-0.0.1.dist-info/top_level.txt
aycolor-0.0.1.dist-info/RECORD
