Metadata-Version: 2.1
Name: aycolor
Version: 0.0.1
Summary: A simple command line coloring tool in python!
Home-page: UNKNOWN
Author: Mohammed Daniyal
Author-email: daniyaldes0@protonmail.com
License: UNKNOWN
Keywords: python,color,terminal
Platform: UNKNOWN
Classifier: Intended Audience :: Developers
Classifier: Programming Language :: Python :: 3
Classifier: Operating System :: Unix
Classifier: Operating System :: MacOS :: MacOS X
Classifier: Operating System :: Microsoft :: Windows
